moldock/__init__.py
moldock/create_pbs_jobs.py
moldock/gen_pdbqt.py
moldock/get_sdf_from_dock_db.py
moldock/gnina_dock.py
moldock/preparation_for_docking.py
moldock/read_input.py
moldock/vina_dock.py
moldock-0.1.3.dist-info/METADATA
moldock-0.1.3.dist-info/WHEEL
moldock-0.1.3.dist-info/entry_points.txt
moldock-0.1.3.dist-info/top_level.txt
moldock-0.1.3.dist-info/RECORD
