Metadata-Version: 2.1
Name: moldock
Version: 0.1.3
Summary: Python moldock to facilitate molecular docking
Home-page: https://github.com/ci-lab-cz/docking-scripts
Author: Pavel Polishchuk
Author-email: pavel_polishchuk@ukr.net
License: UNKNOWN
Platform: UNKNOWN
Classifier: Programming Language :: Python :: 3
Classifier: Operating System :: OS Independent
Classifier: Topic :: Scientific/Engineering :: Bio-Informatics
Classifier: Topic :: Scientific/Engineering :: Chemistry
Requires-Python: >=3.6
Provides-Extra: rdkit
Requires-Dist: rdkit (>=2017.09) ; extra == 'rdkit'
